README.rst
setup.py
claytron/__init__.py
claytron.featuring.egg-info/PKG-INFO
claytron.featuring.egg-info/SOURCES.txt
claytron.featuring.egg-info/dependency_links.txt
claytron.featuring.egg-info/entry_points.txt
claytron.featuring.egg-info/namespace_packages.txt
claytron.featuring.egg-info/not-zip-safe
claytron.featuring.egg-info/requires.txt
claytron.featuring.egg-info/top_level.txt
claytron/featuring/__init__.py
claytron/featuring/script.py
docs/HISTORY.rst