Metadata-Version: 1.0
Name: claytron.featuring
Version: 1.0
Summary: A console script to clean an iTunes library
Home-page: http://claytron.com
Author: Clayton Parker
Author-email: robots@claytron.com
License: GPL
Keywords: itunes metadata
Platform: UNKNOWN
Classifier: Programming Language :: Python
